{
  "ticketLink": "eventbrite.com/e/475326493337/?discount=DNSFAM",
  "linkText": "GUEST LIST",
  "eventDate": "2022-12-09T21:29:39.160Z",
  "eventLocation": "San Francisco, CA",
  "venue": "Public Works Loft",
  "format": "Live",
  "title": "Cazztek",
  "id": "Z8eC1HpBu",
  "description": "Headliner:\n\n► Cazztek\n\n[Linktr.ee/cazztek](Linktr.ee/cazztek)\n\nCazztek is taking the US by storm! Releasing on Tchami’s Confession, Martin Garrix’s STMPED, and Dr. Fresch’s House Call imprint, and receiving DJ support from hundreds of other heavy hitters, Cazztek is a House producer force to be reckoned with. Join us at his first ever San Francisco show!\n\nSupport:\n\n►Kairos\n\n[Instagram.com/itskairosmusic](Instagram.com/itskairosmusic)[](Instagram.com/itskairosmusic)\n\n[Instagram.com/itskairosmusic](Instagram.com/itskairosmusic)\n\n► Wraith\n\n[Instagram.com/timmy_turns](Instagram.com/timmy_turns)[](Soundcloud.com/wraith_music)\n\n[Soundcloud.com/wraith_music](Soundcloud.com/wraith_music)\n\n► SOWR\n\n[Linktr.ee/sowr](Linktr.ee/sowr)\n\n► RE!GN\n\n[Linktr.ee/reignmusic](Linktr.ee/reignmusic)\n\n► Eyezick\n\n[Instagram.com/djeyezick](Instagram.com/djeyezick)[](Soundcloud.com/eyezickmusic)\n\n[Soundcloud.com/eyezickmusic](Soundcloud.com/eyezickmusic)",
  "publishDate": "2022-11-28T21:29:30.538Z",
  "photoUrl": "/public/media/ig-square-cazztek.jpg"
}