{
  "isPromoCodeEnabled": false,
  "id": "xeg4KyyZCk",
  "publishDate": "2025-12-11T12:06:20",
  "eventDate": "2026-01-01T12:06:20.000-08:00",
  "format": "Live",
  "title": "Feral Start w/Dillon Francis",
  "eventLocation": "San Francisco, CA",
  "venue": "The Midway",
  "ticketLink": "https://tixr.com/e/168495",
  "photoUrl": "/media/feral-start-dillon-francis-jan-1-2026-1x1.jpg",
  "description": "Fresh Start x The Midway x Dirty Not Sorry present\n\n**FERAL START** at The Midway \n\nNYE Late NIght: 1-5 AM \n\nDillon Francis \n\nTwin Diplomacy \n\n+ Much more TBA!\n\nAges: 21+ \n",
  "linkText": "TICKETS"
}