{
  "id": "Z7szP15fbM",
  "publishDate": "2023-10-11T14:42:31.383",
  "eventDate": "2023-10-28T14:42:31.000-07:00",
  "format": "Live",
  "title": "Haunted Hawthorn",
  "eventLocation": "San Francisco, CA",
  "venue": "Hawthorn",
  "ticketLink": "https://eventbrite.com/e/733561441017/?discount=DNSFAM",
  "linkText": "TICKETS",
  "photoUrl": "/media/hauntedhawthorn_102823_1080x1080.jpg",
  "description": "Join us for the Halloween 2023 edition of our Hawthorn Residency: Haunted Hawthorn!\n\n\n\n\n\nMain Room:\n\n▶︎ Jaxx T\n\n\n[Linktr.ee/jaxxtofficial](https://www.linktr.ee/jaxxtofficial)\n\n\n\n\n\n\n▶︎ Knives\n\n\n[Linktr.ee/djknives](https://www.linktr.ee/djknives)\n\n\n\n\n\n\n▶︎ Slic3r\n\n\n[Linktr.ee/slic3r](https://www.linktr.ee/slic3r)\n\n\n\n\n\n\nBonaparte Room:\n\n▶︎ Captain Daddy\n\n\n[Instagram.com/captain__daddy](https://www.instagram.com/captain__daddy)\n\n\n\n[Soundcloud.com/captain_daddy](https://www.soundcloud.com/captain_daddy)\n\n\n\n[Linktr.ee/captain__daddy](https://www.linktr.ee/captain__daddy)\n[ddy](https://www.)\n\n\n\n\n\n\n▶︎ i2i\n\n\n[Linktr.ee/i2i](https://www.linktr.ee/i2i)\n\n\n\n\n\n\n▶︎ Legrant\n\n\n[Linktr.ee/legrantmusic](https://www.linktr.ee/legrantmusic)\n\n\n\n[Instagram.com/_legrant](https://www.instagram.com/_legrant)\n\n\n\n[Soundcloud.com/austenluego](https://www.soundcloud.com/austenluego)\n\n\n\n\n\n\n▶︎ Melevate\n\n\n[Instagram.com/melevatemusic](https://www.instagram.com/melevatemusic)\n\n\n\n[Soundcloud.com/melevate](https://www.soundcloud.com/melevate)\n\n\n\n[Linktr.ee/melevatemusic](https://www.linktr.ee/melevatemusic)\n\n"
}