{
  "ticketLink": "fb.me/e/2alNhKGYh",
  "linkText": "RSVP",
  "eventDate": "2023-01-19T00:00:00.000-08:00",
  "eventLocation": "San Francisco, CA",
  "venue": "Twitch",
  "format": "Stream",
  "title": "Press Play Thursday: Biluminati",
  "id": "itsRbng_z",
  "description": "ONLINE EVENT HAPPENING HERE-> [Twitch.com/dirtynotsorry](Twitch.com/dirtynotsorry)\\\n▄▄▄▄▄▄▄▄▄▄▄▄▄▄▄▄\\\nFeaturing:\n\n► Biluminati\\\n[Instagram.com/biluminatimusic](Instagram.com/biluminatimusic)\\\n[Soundcloud.com/biluminati](Soundcloud.com/biluminati)\\\n▄▄▄▄▄▄▄▄▄▄▄▄▄▄▄▄",
  "publishDate": "2023-01-16T20:47:56.862-08:00",
  "photoUrl": "/public/media/19ppjan-sq.jpg"
}