{
  "id": "lmnRop5z_7",
  "publishDate": "2024-01-29T02:12:42.747",
  "eventDate": "2024-02-08T02:12:42.000-06:00",
  "format": "Stream",
  "title": "Wlferal - Press Play Thursday",
  "eventLocation": "Online",
  "venue": "Twitch",
  "ticketLink": "https://fb.me/e/616yIiy9N",
  "linkText": "RSVP",
  "photoUrl": "/media/wlferal-ig-square.jpg",
  "description": "\n[On.Soundcloud.com/xq8HA](https://On.Soundcloud.com/xq8HA)\n\n[Instagram.com/wlferal](https://Instagram.com/wlferal)\n\n[Linkedin.com/in/peternguyen92](https://Linkedin.com/in/peternguyen92)\n\n"
}