{
  "id": "wNk-bh-AiJ",
  "publishDate": "2025-03-17T19:21:57.207-07:00",
  "postDate": "2025-03-17T19:21:57.207-07:00",
  "title": "New Dirty Not Sorry Records Release",
  "subtitle": "Pass Out (Julian Sass Remix) [DNSR002]\n",
  "photoUrl": "/media/tinie-tempah-pass-out-julian-sass-remix-album-cover.png",
  "callToAction": "Click the link to listen and download",
  "callToActionLink": "https://soundcloud.com/dirtynotsorry/tinie-tempah-pass-out-julian-sass-remixdirty-not-sorry-exclusive",
  "callToActionButtonText": "Listen Now",
  "body": "Delivering you the second release from our new label — Dirty Not Sorry Records.\n\nJulian Sass delivers on a high energy remix turning Tinie Tempah's \"Pass Out\" into a hard-hitting club banger.\n"
}